[
  {
    "inputs": [],
    "stateMutability": "nonpayable",
    "type": "constructor"
  },
  {
    "anonymous": false,
    "inputs": [
      {
        "indexed": true,
        "internalType": "string",
        "name": "hash",
        "type": "string"
      },
      {
        "indexed": true,
        "internalType": "address",
        "name": "owner",
        "type": "address"
      }
    ],
    "name": "HashStored",
    "type": "event"
  },
  {
    "anonymous": false,
    "inputs": [
      {
        "indexed": true,
        "internalType": "string",
        "name": "hash",
        "type": "string"
      },
      {
        "indexed": true,
        "internalType": "address",
        "name": "registrar",
        "type": "address"
      }
    ],
    "name": "PropertyApproved",
    "type": "event"
  },
  {
    "anonymous": false,
    "inputs": [
      {
        "indexed": false,
        "internalType": "address",
        "name": "registrar",
        "type": "address"
      },
      {
        "indexed": false,
        "internalType": "string",
        "name": "hash",
        "type": "string"
      }
    ],
    "name": "PropertyApproved",
    "type": "event"
  },
  {
    "anonymous": false,
    "inputs": [
      {
        "indexed": false,
        "internalType": "address",
        "name": "owner",
        "type": "address"
      },
      {
        "indexed": false,
        "internalType": "string",
        "name": "hash",
        "type": "string"
      }
    ],
    "name": "PropertyRegistered",
    "type": "event"
  },
  {
    "anonymous": false,
    "inputs": [
      {
        "indexed": false,
        "internalType": "address",
        "name": "from",
        "type": "address"
      },
      {
        "indexed": false,
        "internalType": "address",
        "name": "to",
        "type": "address"
      },
      {
        "indexed": false,
        "internalType": "string",
        "name": "hash",
        "type": "string"
      }
    ],
    "name": "PropertyTransferred",
    "type": "event"
  },
  {
    "anonymous": false,
    "inputs": [
      {
        "indexed": true,
        "internalType": "address",
        "name": "registrar",
        "type": "address"
      }
    ],
    "name": "RegistrarAdded",
    "type": "event"
  },
  {
    "inputs": [
      {
        "internalType": "address",
        "name": "registrar",
        "type": "address"
      }
    ],
    "name": "addRegistrar",
    "outputs": [],
    "stateMutability": "nonpayable",
    "type": "function"
  },
  {
    "inputs": [],
    "name": "admin",
    "outputs": [
      {
        "internalType": "address",
        "name": "",
        "type": "address"
      }
    ],
    "stateMutability": "view",
    "type": "function"
  },
  {
    "inputs": [
      {
        "internalType": "uint256",
        "name": "",
        "type": "uint256"
      }
    ],
    "name": "allPropertyHashes",
    "outputs": [
      {
        "internalType": "string",
        "name": "",
        "type": "string"
      }
    ],
    "stateMutability": "view",
    "type": "function"
  },
  {
    "inputs": [
      {
        "internalType": "string",
        "name": "hash",
        "type": "string"
      }
    ],
    "name": "approveProperty",
    "outputs": [],
    "stateMutability": "nonpayable",
    "type": "function"
  },
  {
    "inputs": [
      {
        "internalType": "string",
        "name": "",
        "type": "string"
      }
    ],
    "name": "documentOwner",
    "outputs": [
      {
        "internalType": "address",
        "name": "",
        "type": "address"
      }
    ],
    "stateMutability": "view",
    "type": "function"
  },
  {
    "inputs": [],
    "name": "getAllProperties",
    "outputs": [
      {
        "internalType": "string[]",
        "name": "",
        "type": "string[]"
      }
    ],
    "stateMutability": "view",
    "type": "function"
  },
  {
    "inputs": [
      {
        "internalType": "string",
        "name": "hash",
        "type": "string"
      }
    ],
    "name": "getOwner",
    "outputs": [
      {
        "internalType": "address",
        "name": "",
        "type": "address"
      }
    ],
    "stateMutability": "view",
    "type": "function"
  },
  {
    "inputs": [
      {
        "internalType": "string",
        "name": "hash",
        "type": "string"
      }
    ],
    "name": "getPropertyHistory",
    "outputs": [
      {
        "components": [
          {
            "internalType": "address",
            "name": "from",
            "type": "address"
          },
          {
            "internalType": "address",
            "name": "to",
            "type": "address"
          },
          {
            "internalType": "uint256",
            "name": "timestamp",
            "type": "uint256"
          }
        ],
        "internalType": "struct DocumentVault.TransferRecord[]",
        "name": "",
        "type": "tuple[]"
      }
    ],
    "stateMutability": "view",
    "type": "function"
  },
  {
    "inputs": [
      {
        "internalType": "string",
        "name": "",
        "type": "string"
      }
    ],
    "name": "properties",
    "outputs": [
      {
        "internalType": "address",
        "name": "owner",
        "type": "address"
      },
      {
        "internalType": "string",
        "name": "hash",
        "type": "string"
      },
      {
        "internalType": "bool",
        "name": "verified",
        "type": "bool"
      }
    ],
    "stateMutability": "view",
    "type": "function"
  },
  {
    "inputs": [
      {
        "internalType": "string",
        "name": "",
        "type": "string"
      },
      {
        "internalType": "uint256",
        "name": "",
        "type": "uint256"
      }
    ],
    "name": "propertyHistory",
    "outputs": [
      {
        "internalType": "address",
        "name": "from",
        "type": "address"
      },
      {
        "internalType": "address",
        "name": "to",
        "type": "address"
      },
      {
        "internalType": "uint256",
        "name": "timestamp",
        "type": "uint256"
      }
    ],
    "stateMutability": "view",
    "type": "function"
  },
  {
    "inputs": [
      {
        "internalType": "string",
        "name": "hash",
        "type": "string"
      }
    ],
    "name": "registerProperty",
    "outputs": [],
    "stateMutability": "nonpayable",
    "type": "function"
  },
  {
    "inputs": [
      {
        "internalType": "address",
        "name": "",
        "type": "address"
      }
    ],
    "name": "registrars",
    "outputs": [
      {
        "internalType": "bool",
        "name": "",
        "type": "bool"
      }
    ],
    "stateMutability": "view",
    "type": "function"
  },
  {
    "inputs": [
      {
        "internalType": "string",
        "name": "_hash",
        "type": "string"
      }
    ],
    "name": "storeHash",
    "outputs": [],
    "stateMutability": "nonpayable",
    "type": "function"
  },
  {
    "inputs": [
      {
        "internalType": "string",
        "name": "hash",
        "type": "string"
      },
      {
        "internalType": "address",
        "name": "newOwner",
        "type": "address"
      }
    ],
    "name": "transferProperty",
    "outputs": [],
    "stateMutability": "nonpayable",
    "type": "function"
  },
  {
    "inputs": [
      {
        "internalType": "string",
        "name": "_hash",
        "type": "string"
      }
    ],
    "name": "verifyHash",
    "outputs": [
      {
        "internalType": "bool",
        "name": "",
        "type": "bool"
      }
    ],
    "stateMutability": "view",
    "type": "function"
  },
  {
    "inputs": [
      {
        "internalType": "string",
        "name": "hash",
        "type": "string"
      }
    ],
    "name": "verifyProperty",
    "outputs": [
      {
        "internalType": "bool",
        "name": "",
        "type": "bool"
      }
    ],
    "stateMutability": "view",
    "type": "function"
  }
]